tepe/__init__.py
tepe/core/__init__.py
tepe/core/base_evaluator.py
tepe/core/base_predictor.py
tepe/core/base_task.py
tepe/core/base_trainer.py
tepe/core/cli.py
tepe/core/exporter.py
tepe/core/register.py
tepe/core/evaluator/__init__.py
tepe/core/evaluator/cls_evaluator.py
tepe/core/evaluator/seg_evaluator.py
tepe/core/evaluator/metrics/__init__.py
tepe/core/evaluator/metrics/cls_metrics.py
tepe/core/evaluator/metrics/seg_metrics.py
tepe/core/evaluator/metrics/voc_metrics.py
tepe/core/predictor/__init__.py
tepe/core/predictor/anomaly_detector.py
tepe/core/predictor/classifier.py
tepe/core/predictor/segmentor.py
tepe/core/trainer/__init__.py
tepe/core/trainer/cls_trainer.py
tepe/core/trainer/seg_trainer.py
tepe/data/__init__.py
tepe/data/augmentations.py
tepe/data/data_prefetcher.py
tepe/data/dataloading.py
tepe/data/infer_datasets.py
tepe/data/utils.py
tepe/data/annotation/__init__.py
tepe/data/annotation/labelme_json.py
tepe/data/annotation/voc_xml.py
tepe/data/augments/__init__.py
tepe/data/augments/paste_images.py
tepe/data/augments/seg_augment.py
tepe/data/datasets/__init__.py
tepe/data/datasets/ad_dataset.py
tepe/data/datasets/cls_datasets.py
tepe/data/datasets/keypoint_dataset.py
tepe/data/datasets/line_dataset.py
tepe/data/datasets/public_class_names.py
tepe/data/datasets/seg_voc_custom.py
tepe/data/datasets/ssdrfb_voc.py
tepe/modules/__init__.py
tepe/modules/activation.py
tepe/modules/init_weights.py
tepe/modules/layers.py
tepe/modules/loss.py
tepe/modules/model_utils.py
tepe/modules/model_zoo.py
tepe/modules/backbone/__init__.py
tepe/modules/backbone/mobilenet_rfb.py
tepe/modules/backbone/mobilenetv2.py
tepe/modules/backbone/resnet.py
tepe/modules/backbone/shufflenetv2.py
tepe/modules/backbone/simplenet.py
tepe/modules/backbone/vgg.py
tepe/modules/neck/__init__.py
tepe/modules/neck/fpn.py
tepe/modules/neck/pan.py
tepe/modules/optim/__init__.py
tepe/modules/optim/adabelief.py
tepe/modules/optim/adafactor.py
tepe/modules/optim/adahessian.py
tepe-0.7.5.2.dist-info/LICENSE
tepe-0.7.5.2.dist-info/METADATA
tepe-0.7.5.2.dist-info/WHEEL
tepe-0.7.5.2.dist-info/entry_points.txt
tepe-0.7.5.2.dist-info/top_level.txt
tepe-0.7.5.2.dist-info/RECORD
