Metadata-Version: 2.1
Name: tepe
Version: 0.7.5.2
Summary: A concise and unified toolkit for Training, Evalutation, Prediction and Export (TEPE)
Home-page: UNKNOWN
Author: Lenovo Reaserch SD&S
License: UNKNOWN
Platform: UNKNOWN
Classifier: Operating System :: OS Independent
Classifier: Programming Language :: Python :: 3 :: Only
Requires-Python: >=3.8
License-File: LICENSE
Requires-Dist: albumentations
Requires-Dist: loguru
Requires-Dist: addict
Requires-Dist: tabulate
Requires-Dist: PyYAML
Requires-Dist: lxml
